sphinx_pyppeteer_builder/__init__.py
sphinx_pyppeteer_builder/loghandler.py
sphinx_pyppeteer_builder/pyppeteer_builder.py
sphinx_pyppeteer_builder/locale/sphinx.pot
sphinx_pyppeteer_builder/locale/fr/LC_MESSAGES/sphinx.po
sphinx_pyppeteer_builder-1.0.0.dist-info/entry_points.txt
sphinx_pyppeteer_builder-1.0.0.dist-info/LICENSE
sphinx_pyppeteer_builder-1.0.0.dist-info/LICENSE-de
sphinx_pyppeteer_builder-1.0.0.dist-info/LICENSE-fr
sphinx_pyppeteer_builder-1.0.0.dist-info/LICENSE-nl
sphinx_pyppeteer_builder-1.0.0.dist-info/WHEEL
sphinx_pyppeteer_builder-1.0.0.dist-info/METADATA
sphinx_pyppeteer_builder-1.0.0.dist-info/RECORD
