Metadata-Version: 2.1
Name: sphinx_pyppeteer_builder
Version: 1.0.0
Summary: A Sphinx PDF builder using pyppeteer
Keywords: sphinx,doc,pdf,pyppeteer
Author: kujiu, ptitgnu
Author-email: Nerv Project ASBL <contact@nerv-project.eu>
Maintainer: kujiu, ptitgnu
Maintainer-email: Nerv Project ASBL <contact@nerv-project.eu>
Requires-Python: >=3.8
Classifier: Framework :: Sphinx
Classifier: Framework :: Sphinx :: Extension
Classifier: Development Status :: 5 - Production/Stable
Classifier: License :: OSI Approved :: European Union Public Licence 1.2 (EUPL 1.2)
Classifier: Environment :: Console
Classifier: Environment :: Web Environment
Classifier: Intended Audience :: Developers
Classifier: Programming Language :: Python :: 3
Classifier: Operating System :: OS Independent
Classifier: Topic :: Documentation
Classifier: Topic :: Software Development :: Documentation
Requires-Dist: Sphinx>=7.0.0
Requires-Dist: pyppeteer
Requires-Dist: typing_extensions
Requires-Dist: Sphinx ; extra == "setup"
Requires-Dist: pytest-runner ; extra == "setup"
Requires-Dist: pyright ; extra == "setup"
Requires-Dist: pylint ; extra == "setup"
Requires-Dist: babel ; extra == "setup"
Requires-Dist: flit ; extra == "setup"
Requires-Dist: pytest ; extra == "tests"
Requires-Dist: pyright ; extra == "tests"
Requires-Dist: pylint ; extra == "tests"
Requires-Dist: pytest-cov ; extra == "tests"
Project-URL: changelog, https://procrastinator.nerv-project.eu/nerv-project/sphinx_pyppeteer_builder/raw/branch/main/CHANGES.rst
Project-URL: editor, https://www.nerv-project.eu
Project-URL: homepage, https://www.nerv-project.eu
Project-URL: issues, https://procrastinator.nerv-project.eu/nerv-project/sphinx_pyppeteer_builder/issues
Project-URL: repository, https://procrastinator.nerv-project.eu/nerv-project/sphinx_pyppeteer_builder
Provides-Extra: setup
Provides-Extra: tests
